jlcards-0.0.8.data/data/etc/jupyter/jupyter_notebook_config.d/jlmc.json
jlcards-0.0.8.data/data/etc/jupyter/jupyter_server_config.d/jlmc.json
jlcards-0.0.8.data/data/share/jupyter/labextensions/jlmc/install.json
jlcards-0.0.8.data/data/share/jupyter/labextensions/jlmc/package.json
jlcards-0.0.8.data/data/share/jupyter/labextensions/jlmc/static/163.3e183cc23ba813667994.js
jlcards-0.0.8.data/data/share/jupyter/labextensions/jlmc/static/163.3e183cc23ba813667994.js.LICENSE.txt
jlcards-0.0.8.data/data/share/jupyter/labextensions/jlmc/static/172.5c064f9af0b278ea71e8.js
jlcards-0.0.8.data/data/share/jupyter/labextensions/jlmc/static/270.9a67d63023c31ab6be45.js
jlcards-0.0.8.data/data/share/jupyter/labextensions/jlmc/static/270.9a67d63023c31ab6be45.js.LICENSE.txt
jlcards-0.0.8.data/data/share/jupyter/labextensions/jlmc/static/336.e9a4b7c9081307d38745.js
jlcards-0.0.8.data/data/share/jupyter/labextensions/jlmc/static/44.5ba88485e511d5dc50e6.js
jlcards-0.0.8.data/data/share/jupyter/labextensions/jlmc/static/456.1c336aed2f88e16a6b2a.js
jlcards-0.0.8.data/data/share/jupyter/labextensions/jlmc/static/456.1c336aed2f88e16a6b2a.js.LICENSE.txt
jlcards-0.0.8.data/data/share/jupyter/labextensions/jlmc/static/479.3de39144c2ea9ecb3b59.js
jlcards-0.0.8.data/data/share/jupyter/labextensions/jlmc/static/532.a2de02be4c84197d64ba.js
jlcards-0.0.8.data/data/share/jupyter/labextensions/jlmc/static/549.504770e595e075b79eda.js
jlcards-0.0.8.data/data/share/jupyter/labextensions/jlmc/static/57.f975a13e93882aa63dcf.js
jlcards-0.0.8.data/data/share/jupyter/labextensions/jlmc/static/700.6922404e159f210e7ab6.js
jlcards-0.0.8.data/data/share/jupyter/labextensions/jlmc/static/895.3323a09e769f687a149f.js
jlcards-0.0.8.data/data/share/jupyter/labextensions/jlmc/static/895.3323a09e769f687a149f.js.LICENSE.txt
jlcards-0.0.8.data/data/share/jupyter/labextensions/jlmc/static/remoteEntry.f63f8abbd88841299aa7.js
jlcards-0.0.8.data/data/share/jupyter/labextensions/jlmc/static/style.js
jlcards-0.0.8.dist-info/LICENSE
jlcards-0.0.8.dist-info/METADATA
jlcards-0.0.8.dist-info/WHEEL
jlcards-0.0.8.dist-info/top_level.txt
jlcards-0.0.8.dist-info/RECORD
